Covalent/Balances.py
Covalent/NFT.py
Covalent/Transactions.py
Covalent/__init__.py
Covalent/covalant_helper.py
Zora/__init__.py
Zora/agg_att.py
Zora/agg_stats.py
Zora/collections_metadata.py
Zora/events.py
Zora/mints.py
Zora/off_chain.py
Zora/sales.py
Zora/search.py
Zora/tokens.py
Zora/url.py
Zora/zora_helper.py
mode/__init__.py
mode/mode_helper.py
mode/testnet.py
Web3toolskit-1.0.1.dist-info/METADATA
Web3toolskit-1.0.1.dist-info/WHEEL
Web3toolskit-1.0.1.dist-info/top_level.txt
Web3toolskit-1.0.1.dist-info/RECORD
